Metadata-Version: 2.1
Name: rec4torch
Version: 0.0.2
Summary: an elegant rec4torch
Home-page: https://github.com/Tongjilibo/rec4torch
Author: Tongjilibo
License: MIT Licence
License-File: LICENSE
